qmcp/__init__.py
qmcp/auth.py
qmcp/cloud_api.py
qmcp/config.py
qmcp/config_template.toml
qmcp/qcomms.py
qmcp/qlib.py
qmcp/qmcp.q
qmcp/qmcphelp.py
qmcp/qythonhelp.py
qmcp/server.py
qmcp/translate.py
qmcp/util.py
qmcp/docs/home.md
qmcp/parseq/__init__.py
qmcp/parseq/callLLM.py
qmcp/parseq/disambiguate.py
qmcp/parseq/parseq.py
qmcp/parseq/parseq.q
qmcp/parseq/parseq_ns.q
qmcp/parseq/q_operators.md
qmcp/qpython/__init__.py
qmcp/qpython/_pandas.py
qmcp/qpython/fastutils.pyx
qmcp/qpython/qcollection.py
qmcp/qpython/qconnection.py
qmcp/qpython/qmetaconversion.py
qmcp/qpython/qreader.py
qmcp/qpython/qtemporal.py
qmcp/qpython/qtype.py
qmcp/qpython/qtypes.py
qmcp/qpython/qwriter.py
qmcp/qpython/utils.py
qmcp/qython/docs_api.py
qmcp/qython/q_utils.py
qmcp/qython/qython.q
qmcp/qython/docs/advanced_db.md
qmcp/qython/docs/advanced_string.md
qmcp/qython/docs/data_engineering.md
qmcp/qython/docs/home.md
qmcp/qython/docs/home_db.md
qmcp/qython/docs/home_numpy.md
qmcp/qython/docs/lstsq.md
qmcp/qython/docs/passthrough.md
qmcp/qython/docs/timer.md
qmcp-0.7.5.dist-info/licenses/LICENSE
qmcp-0.7.5.dist-info/licenses/NOTICE
qmcp-0.7.5.dist-info/METADATA
qmcp-0.7.5.dist-info/WHEEL
qmcp-0.7.5.dist-info/entry_points.txt
qmcp-0.7.5.dist-info/top_level.txt
qmcp-0.7.5.dist-info/RECORD
