Metadata-Version: 2.4
Name: qmcp
Version: 0.7.5
Summary: MCP Server for q/kdb+ integration (Cloud-connected client)
Author-email: Gabi Teodoru <gabiteodoru@gmail.com>
License: Apache-2.0
Project-URL: Homepage, https://medium.com/@gabiteodoru/why-llms-cant-write-q-kdb-writing-code-right-to-left-ea6df68af443
Project-URL: Documentation, https://medium.com/@gabiteodoru
Project-URL: Bug Tracker, https://github.com/gabiteodoru/qmcp/issues
Requires-Python: >=3.8
License-File: LICENSE
License-File: NOTICE
Requires-Dist: mcp
Requires-Dist: requests>=2.32.0
Requires-Dist: numpy>=1.8.0
Requires-Dist: pandas
Requires-Dist: msgpack>=1.0.0
Requires-Dist: gabiteodoru-sugar
Requires-Dist: platformdirs>=3.0.0
Requires-Dist: tomli>=1.2.0; python_version < "3.11"
Requires-Dist: ordered-set>=4.0.0
Requires-Dist: psutil>=5.0.0
Provides-Extra: test
Requires-Dist: pytest>=6.0; extra == "test"
Dynamic: license-file
